chaosservicefabric/__init__.py
chaosservicefabric/cluster/__init__.py
chaosservicefabric/cluster/actions.py
chaosservicefabric/cluster/probes.py
chaosservicefabric/types.py
chaostoolkit_service_fabric-0.3.1.dist-info/METADATA
chaostoolkit_service_fabric-0.3.1.dist-info/WHEEL
chaostoolkit_service_fabric-0.3.1.dist-info/licenses/LICENSE
chaostoolkit_service_fabric-0.3.1.dist-info/RECORD
